[
  {
    "issuer_ca_id": 295810,
    "issuer_name": "C=US, O=Let's Encrypt, CN=E5",
    "common_name": "whitehouse.gov",
    "name_value": "whitehouse.gov\nwww.whitehouse.gov",
    "id": 18598060653,
    "entry_timestamp": "2025-05-24T15:05:35.244",
    "not_before": "2025-05-24T14:07:00",
    "not_after": "2025-08-22T14:06:59",
    "serial_number": "06e7cbf5ad81db8e493c6cc62fb35b985663",
    "result_count": 3
  },
  {
    "issuer_ca_id": 295810,
    "issuer_name": "C=US, O=Let's Encrypt, CN=E5",
    "common_name": "whitehouse.gov",
    "name_value": "whitehouse.gov\nwww.whitehouse.gov",
    "id": 18598061081,
    "entry_timestamp": "2025-05-24T15:05:31.19",
    "not_before": "2025-05-24T14:07:00",
    "not_after": "2025-08-22T14:06:59",
    "serial_number": "06e7cbf5ad81db8e493c6cc62fb35b985663",
    "result_count": 3
  },
  {
    "issuer_ca_id": 295810,
    "issuer_name": "C=US, O=Let's Encrypt, CN=E5",
    "common_name": "tours.whitehouse.gov",
    "name_value": "tours.whitehouse.gov",
    "id": 18580375243,
    "entry_timestamp": "2025-05-23T16:29:56.763",
    "not_before": "2025-05-23T15:31:22",
    "not_after": "2025-08-21T15:31:21",
    "serial_number": "066b83626ea5ca881afd374245178c1514cf",
    "result_count": 2
  },
  {
    "issuer_ca_id": 295810,
    "issuer_name": "C=US, O=Let's Encrypt, CN=E5",
    "common_name": "tours.whitehouse.gov",
    "name_value": "tours.whitehouse.gov",
    "id": 18580376296,
    "entry_timestamp": "2025-05-23T16:29:52.408",
    "not_before": "2025-05-23T15:31:22",
    "not_after": "2025-08-21T15:31:21",
    "serial_number": "066b83626ea5ca881afd374245178c1514cf",
    "result_count": 2
  },
  {
    "issuer_ca_id": 217001,
    "issuer_name": "C=US, O=\"DigiCert, Inc.\", CN=DigiCert Verified Mark RSA4096 SHA256 2021 CA1",
    "common_name": "Executive Office of the President",
    "name_value": "whitehouse.gov",
    "id": 18305926719,
    "entry_timestamp": "2025-05-08T21:24:11.487",
    "not_before": "2025-05-06T00:00:00",
    "not_after": "2026-05-06T23:59:59",
    "serial_number": "0e0b4aaa20404adef9f8ad3b3fd319fc",
    "result_count": 1
  },
  {
    "issuer_ca_id": 217001,
    "issuer_name": "C=US, O=\"DigiCert, Inc.\", CN=DigiCert Verified Mark RSA4096 SHA256 2021 CA1",
    "common_name": "Executive Office of the President",
    "name_value": "whitehouse.gov",
    "id": 18265971321,
    "entry_timestamp": "2025-05-06T17:32:04.577",
    "not_before": "2025-05-06T00:00:00",
    "not_after": "2026-05-06T23:59:59",
    "serial_number": "0e0b4aaa20404adef9f8ad3b3fd319fc",
    "result_count": 1
  },
  {
    "issuer_ca_id": 286236,
    "issuer_name": "C=US, O=Google Trust Services, CN=WE1",
    "common_name": "whitehouse.gov",
    "name_value": "*.whitehouse.gov\nwhitehouse.gov",
    "id": 18189812752,
    "entry_timestamp": "2025-05-02T23:35:51.704",
    "not_before": "2025-05-02T22:35:51",
    "not_after": "2025-07-31T23:28:47",
    "serial_number": "00b709a92940534e291137b8f435d319a6",
    "result_count": 3
  },
  {
    "issuer_ca_id": 295819,
    "issuer_name": "C=US, O=Let's Encrypt, CN=E6",
    "common_name": "visit.whitehouse.gov",
    "name_value": "visit.whitehouse.gov",
    "id": 18082187655,
    "entry_timestamp": "2025-04-26T23:58:23.563",
    "not_before": "2025-04-26T22:59:53",
    "not_after": "2025-07-25T22:59:52",
    "serial_number": "05ec351ca8eafe3b92217c38bd2fc730cc20",
    "result_count": 2
  },
  {
    "issuer_ca_id": 295819,
    "issuer_name": "C=US, O=Let's Encrypt, CN=E6",
    "common_name": "visit.whitehouse.gov",
    "name_value": "visit.whitehouse.gov",
    "id": 18082193514,
    "entry_timestamp": "2025-04-26T23:58:23.446",
    "not_before": "2025-04-26T22:59:53",
    "not_after": "2025-07-25T22:59:52",
    "serial_number": "05ec351ca8eafe3b92217c38bd2fc730cc20",
    "result_count": 2
  },
  {
    "issuer_ca_id": 105484,
    "issuer_name": "C=GB, ST=Greater Manchester, L=Salford, O=Sectigo Limited, CN=Sectigo ECC Domain Validation Secure Server CA",
    "common_name": "whitehouse.gov",
    "name_value": "*.whitehouse.gov\nwhitehouse.gov",
    "id": 17812866685,
    "entry_timestamp": "2025-04-13T00:31:29.898",
    "not_before": "2025-04-13T00:00:00",
    "not_after": "2025-07-12T00:13:24",
    "serial_number": "00d6a819d5523e190334c1a4e6bf74f92a",
    "result_count": 3
  },
  {
    "issuer_ca_id": 105484,
    "issuer_name": "C=GB, ST=Greater Manchester, L=Salford, O=Sectigo Limited, CN=Sectigo ECC Domain Validation Secure Server CA",
    "common_name": "whitehouse.gov",
    "name_value": "*.whitehouse.gov\nwhitehouse.gov",
    "id": 17812867351,
    "entry_timestamp": "2025-04-13T00:31:26.593",
    "not_before": "2025-04-13T00:00:00",
    "not_after": "2025-07-12T00:13:24",
    "serial_number": "00d6a819d5523e190334c1a4e6bf74f92a",
    "result_count": 3
  },
  {
    "issuer_ca_id": 295810,
    "issuer_name": "C=US, O=Let's Encrypt, CN=E5",
    "common_name": "joinus.whitehouse.gov",
    "name_value": "joinus.whitehouse.gov",
    "id": 17812391279,
    "entry_timestamp": "2025-04-12T23:53:00.146",
    "not_before": "2025-04-12T22:54:29",
    "not_after": "2025-07-11T22:54:28",
    "serial_number": "0511c78411a81f27ac4d1b7500c740535c94",
    "result_count": 2
  },
  {
    "issuer_ca_id": 295810,
    "issuer_name": "C=US, O=Let's Encrypt, CN=E5",
    "common_name": "joinus.whitehouse.gov",
    "name_value": "joinus.whitehouse.gov",
    "id": 17812391080,
    "entry_timestamp": "2025-04-12T23:52:59.189",
    "not_before": "2025-04-12T22:54:29",
    "not_after": "2025-07-11T22:54:28",
    "serial_number": "0511c78411a81f27ac4d1b7500c740535c94",
    "result_count": 2
  },
  {
    "issuer_ca_id": 62123,
    "issuer_name": "C=US, O=DigiCert Inc, OU=www.digicert.com, CN=GeoTrust TLS RSA CA G1",
    "common_name": "uis.uat.usajobs.gov",
    "name_value": "fellows.whitehouse.gov",
    "id": 17543021841,
    "entry_timestamp": "2025-04-01T00:07:12.961",
    "not_before": "2025-04-01T00:00:00",
    "not_after": "2026-04-01T23:59:59",
    "serial_number": "041e377c89fcf8ce4436c0a4f9399d72",
    "result_count": 1
  },
  {
    "issuer_ca_id": 295810,
    "issuer_name": "C=US, O=Let's Encrypt, CN=E5",
    "common_name": "whitehouse.gov",
    "name_value": "whitehouse.gov\nwww.whitehouse.gov",
    "id": 17345778712,
    "entry_timestamp": "2025-03-23T16:03:47.713",
    "not_before": "2025-03-23T15:05:17",
    "not_after": "2025-06-21T15:05:16",
    "serial_number": "05158a356316e0e19007ddc2fa7c8fcd3b08",
    "result_count": 3
  },
  {
    "issuer_ca_id": 295810,
    "issuer_name": "C=US, O=Let's Encrypt, CN=E5",
    "common_name": "whitehouse.gov",
    "name_value": "whitehouse.gov\nwww.whitehouse.gov",
    "id": 17345782591,
    "entry_timestamp": "2025-03-23T16:03:47.606",
    "not_before": "2025-03-23T15:05:17",
    "not_after": "2025-06-21T15:05:16",
    "serial_number": "05158a356316e0e19007ddc2fa7c8fcd3b08",
    "result_count": 3
  },
  {
    "issuer_ca_id": 295819,
    "issuer_name": "C=US, O=Let's Encrypt, CN=E6",
    "common_name": "tours.whitehouse.gov",
    "name_value": "tours.whitehouse.gov",
    "id": 17321605090,
    "entry_timestamp": "2025-03-22T17:28:15.28",
    "not_before": "2025-03-22T16:29:45",
    "not_after": "2025-06-20T16:29:44",
    "serial_number": "05300eceb3d328d4cde820d455680fb9308d",
    "result_count": 2
  },
  {
    "issuer_ca_id": 295819,
    "issuer_name": "C=US, O=Let's Encrypt, CN=E6",
    "common_name": "tours.whitehouse.gov",
    "name_value": "tours.whitehouse.gov",
    "id": 17321610467,
    "entry_timestamp": "2025-03-22T17:28:15.117",
    "not_before": "2025-03-22T16:29:45",
    "not_after": "2025-06-20T16:29:44",
    "serial_number": "05300eceb3d328d4cde820d455680fb9308d",
    "result_count": 2
  },
  {
    "issuer_ca_id": 185752,
    "issuer_name": "C=US, O=DigiCert Inc, CN=DigiCert Global G2 TLS RSA SHA256 2020 CA1",
    "common_name": "tours.whitehouse.gov",
    "name_value": "tours.whitehouse.gov",
    "id": 15459255605,
    "entry_timestamp": "2024-11-22T22:05:37.236",
    "not_before": "2024-11-22T00:00:00",
    "not_after": "2025-12-23T23:59:59",
    "serial_number": "05b5eeb7582ae44d87bf63d7446a774a",
    "result_count": 2
  },
  {
    "issuer_ca_id": 185752,
    "issuer_name": "C=US, O=DigiCert Inc, CN=DigiCert Global G2 TLS RSA SHA256 2020 CA1",
    "common_name": "events.whitehouse.gov",
    "name_value": "events.whitehouse.gov",
    "id": 15459229738,
    "entry_timestamp": "2024-11-22T22:03:56.149",
    "not_before": "2024-11-22T00:00:00",
    "not_after": "2025-12-23T23:59:59",
    "serial_number": "0178268faf3b6bd5b082c4271037b35b",
    "result_count": 2
  },
  {
    "issuer_ca_id": 185752,
    "issuer_name": "C=US, O=DigiCert Inc, CN=DigiCert Global G2 TLS RSA SHA256 2020 CA1",
    "common_name": "apply.communities.whitehouse.gov",
    "name_value": "apply.communities.whitehouse.gov",
    "id": 15459045056,
    "entry_timestamp": "2024-11-22T21:39:02.138",
    "not_before": "2024-11-22T00:00:00",
    "not_after": "2025-12-23T23:59:59",
    "serial_number": "0e56465ae2a06d00716eb7126da29e99",
    "result_count": 2
  },
  {
    "issuer_ca_id": 185752,
    "issuer_name": "C=US, O=DigiCert Inc, CN=DigiCert Global G2 TLS RSA SHA256 2020 CA1",
    "common_name": "apply.whitehouse.gov",
    "name_value": "apply.whitehouse.gov",
    "id": 15458853477,
    "entry_timestamp": "2024-11-22T21:10:19.503",
    "not_before": "2024-11-22T00:00:00",
    "not_after": "2025-12-23T23:59:59",
    "serial_number": "0c08d6d9f1a5f67e285e4703ff374a37",
    "result_count": 2
  }
]