[
  {
    "issuer_ca_id": 185748,
    "issuer_name": "C=US, O=DigiCert Inc, CN=DigiCert Global G3 TLS ECC SHA384 2020 CA1",
    "common_name": "*.uat.usajobs.gov",
    "name_value": "*.uat.usajobs.gov\nuat.usajobs.gov",
    "id": 21655811230,
    "entry_timestamp": "2025-10-12T00:14:21.778",
    "not_before": "2025-10-12T00:00:00",
    "not_after": "2026-10-13T23:59:59",
    "serial_number": "0d679627a3ee23da32ce3f705a5bfe88",
    "result_count": 3
  },
  {
    "issuer_ca_id": 185748,
    "issuer_name": "C=US, O=DigiCert Inc, CN=DigiCert Global G3 TLS ECC SHA384 2020 CA1",
    "common_name": "*.test.usajobs.gov",
    "name_value": "*.test.usajobs.gov\ntest.usajobs.gov",
    "id": 21655811662,
    "entry_timestamp": "2025-10-12T00:14:04.205",
    "not_before": "2025-10-12T00:00:00",
    "not_after": "2026-10-13T23:59:59",
    "serial_number": "01fae86c2a9d78de2c443e8549ab2588",
    "result_count": 3
  },
  {
    "issuer_ca_id": 185752,
    "issuer_name": "C=US, O=DigiCert Inc, CN=DigiCert Global G2 TLS RSA SHA256 2020 CA1",
    "common_name": "*.uat.usajobs.gov",
    "name_value": "*.uat.usajobs.gov\nuat.usajobs.gov",
    "id": 21655749660,
    "entry_timestamp": "2025-10-12T00:10:10.602",
    "not_before": "2025-10-12T00:00:00",
    "not_after": "2026-10-13T23:59:59",
    "serial_number": "0c8196c70f8baf81a3501dd0fab16e96",
    "result_count": 3
  },
  {
    "issuer_ca_id": 185752,
    "issuer_name": "C=US, O=DigiCert Inc, CN=DigiCert Global G2 TLS RSA SHA256 2020 CA1",
    "common_name": "*.test.usajobs.gov",
    "name_value": "*.test.usajobs.gov\ntest.usajobs.gov",
    "id": 21655749681,
    "entry_timestamp": "2025-10-12T00:09:45.278",
    "not_before": "2025-10-12T00:00:00",
    "not_after": "2026-10-13T23:59:59",
    "serial_number": "07d22a3278fe1cea3f93a443cbca86aa",
    "result_count": 3
  },
  {
    "issuer_ca_id": 185748,
    "issuer_name": "C=US, O=DigiCert Inc, CN=DigiCert Global G3 TLS ECC SHA384 2020 CA1",
    "common_name": "*.dev.usajobs.gov",
    "name_value": "*.dev.usajobs.gov\ndev.usajobs.gov",
    "id": 21221594250,
    "entry_timestamp": "2025-09-23T12:37:02.464",
    "not_before": "2025-04-13T00:00:00",
    "not_after": "2026-04-15T23:59:59",
    "serial_number": "02f4d9e8abb9b162cb61db06894eb652",
    "result_count": 3
  },
  {
    "issuer_ca_id": 185752,
    "issuer_name": "C=US, O=DigiCert Inc, CN=DigiCert Global G2 TLS RSA SHA256 2020 CA1",
    "common_name": "*.dev.usajobs.gov",
    "name_value": "*.dev.usajobs.gov\ndev.usajobs.gov",
    "id": 21221594243,
    "entry_timestamp": "2025-09-23T12:36:50.478",
    "not_before": "2025-09-23T00:00:00",
    "not_after": "2026-10-24T23:59:59",
    "serial_number": "0a18697d87dbf1ac6b191ddaad2af559",
    "result_count": 3
  },
  {
    "issuer_ca_id": 185752,
    "issuer_name": "C=US, O=DigiCert Inc, CN=DigiCert Global G2 TLS RSA SHA256 2020 CA1",
    "common_name": "*.test.usajobs.gov",
    "name_value": "*.test.usajobs.gov\ntest.usajobs.gov",
    "id": 21221496765,
    "entry_timestamp": "2025-09-23T12:30:15.307",
    "not_before": "2025-09-23T00:00:00",
    "not_after": "2026-10-24T23:59:59",
    "serial_number": "04eb1b8d0a5dee3fb32cdbea4e859158",
    "result_count": 3
  },
  {
    "issuer_ca_id": 185752,
    "issuer_name": "C=US, O=DigiCert Inc, CN=DigiCert Global G2 TLS RSA SHA256 2020 CA1",
    "common_name": "*.usajobs.gov",
    "name_value": "*.usajobs.gov\nusajobs.gov",
    "id": 21221403253,
    "entry_timestamp": "2025-09-23T12:25:18.278",
    "not_before": "2025-09-23T00:00:00",
    "not_after": "2026-10-24T23:59:59",
    "serial_number": "094637ea173473d7bf709a7b1bdf2ab8",
    "result_count": 3
  },
  {
    "issuer_ca_id": 185752,
    "issuer_name": "C=US, O=DigiCert Inc, CN=DigiCert Global G2 TLS RSA SHA256 2020 CA1",
    "common_name": "*.UAT.USAJOBS.GOV",
    "name_value": "*.UAT.USAJOBS.GOV\nUAT.USAJOBS.GOV",
    "id": 21206093380,
    "entry_timestamp": "2025-09-22T19:14:55.279",
    "not_before": "2025-09-22T00:00:00",
    "not_after": "2026-10-23T23:59:59",
    "serial_number": "0bcc9235dc8a1e5e3df7ae3602068da3",
    "result_count": 3
  },
  {
    "issuer_ca_id": 185756,
    "issuer_name": "C=US, O=DigiCert Inc, CN=DigiCert TLS RSA SHA256 2020 CA1",
    "common_name": "*.test.usajobs.gov",
    "name_value": "*.test.usajobs.gov\ntest.usajobs.gov",
    "id": 20885936167,
    "entry_timestamp": "2025-09-09T00:44:02.112",
    "not_before": "2024-12-08T00:00:00",
    "not_after": "2025-12-10T23:59:59",
    "serial_number": "05417a4f26254661e8268e3dbe125c56",
    "result_count": 3
  },
  {
    "issuer_ca_id": 62123,
    "issuer_name": "C=US, O=DigiCert Inc, OU=www.digicert.com, CN=GeoTrust TLS RSA CA G1",
    "common_name": "www.employeeexpress.gov",
    "name_value": "developer.drtest.usajobs.gov\nwww.agencyportal.dev.usajobs.gov\nwww.agencyportal.test.usajobs.gov\nwww.agencyportal.uat.usajobs.gov\nwww.agencyportal.usajobs.gov",
    "id": 20839524044,
    "entry_timestamp": "2025-09-07T00:36:46.336",
    "not_before": "2025-08-13T00:00:00",
    "not_after": "2026-08-12T23:59:59",
    "serial_number": "01de06c609e932698affbead2e0d6a75",
    "result_count": 5
  },
  {
    "issuer_ca_id": 185752,
    "issuer_name": "C=US, O=DigiCert Inc, CN=DigiCert Global G2 TLS RSA SHA256 2020 CA1",
    "common_name": "*.usajobs.gov",
    "name_value": "*.usajobs.gov\nusajobs.gov",
    "id": 20839297922,
    "entry_timestamp": "2025-09-07T00:19:10.542",
    "not_before": "2025-09-07T00:00:00",
    "not_after": "2026-09-08T23:59:59",
    "serial_number": "08a05d403d091ce7b0d6f05880d42283",
    "result_count": 3
  },
  {
    "issuer_ca_id": 62123,
    "issuer_name": "C=US, O=DigiCert Inc, OU=www.digicert.com, CN=GeoTrust TLS RSA CA G1",
    "common_name": "www.employeeexpress.gov",
    "name_value": "developer.drtest.usajobs.gov\nwww.agencyportal.dev.usajobs.gov\nwww.agencyportal.test.usajobs.gov\nwww.agencyportal.uat.usajobs.gov\nwww.agencyportal.usajobs.gov",
    "id": 20308285035,
    "entry_timestamp": "2025-08-13T13:05:27.012",
    "not_before": "2025-08-13T00:00:00",
    "not_after": "2026-08-12T23:59:59",
    "serial_number": "01de06c609e932698affbead2e0d6a75",
    "result_count": 5
  },
  {
    "issuer_ca_id": 185756,
    "issuer_name": "C=US, O=DigiCert Inc, CN=DigiCert TLS RSA SHA256 2020 CA1",
    "common_name": "*.usajobs.gov",
    "name_value": "*.usajobs.gov\nusajobs.gov",
    "id": 19510229073,
    "entry_timestamp": "2025-07-07T14:59:21.516",
    "not_before": "2024-11-05T00:00:00",
    "not_after": "2025-11-05T23:59:59",
    "serial_number": "0ffdb1dc64282610aa08b6a045fd6465",
    "result_count": 3
  },
  {
    "issuer_ca_id": 185748,
    "issuer_name": "C=US, O=DigiCert Inc, CN=DigiCert Global G3 TLS ECC SHA384 2020 CA1",
    "common_name": "*.dev.usajobs.gov",
    "name_value": "*.dev.usajobs.gov\ndev.usajobs.gov",
    "id": 17812671924,
    "entry_timestamp": "2025-04-13T00:16:29.732",
    "not_before": "2025-04-13T00:00:00",
    "not_after": "2026-04-15T23:59:59",
    "serial_number": "02f4d9e8abb9b162cb61db06894eb652",
    "result_count": 3
  },
  {
    "issuer_ca_id": 185752,
    "issuer_name": "C=US, O=DigiCert Inc, CN=DigiCert Global G2 TLS RSA SHA256 2020 CA1",
    "common_name": "*.dev.usajobs.gov",
    "name_value": "*.dev.usajobs.gov\ndev.usajobs.gov",
    "id": 17812554562,
    "entry_timestamp": "2025-04-13T00:08:08.892",
    "not_before": "2025-04-13T00:00:00",
    "not_after": "2026-04-15T23:59:59",
    "serial_number": "0ce673efcb9bb63c2527bfeca83c867c",
    "result_count": 3
  },
  {
    "issuer_ca_id": 185756,
    "issuer_name": "C=US, O=DigiCert Inc, CN=DigiCert TLS RSA SHA256 2020 CA1",
    "common_name": "*.uat.usajobs.gov",
    "name_value": "*.uat.usajobs.gov\nuat.usajobs.gov",
    "id": 17543021963,
    "entry_timestamp": "2025-04-01T00:07:29.143",
    "not_before": "2024-12-10T00:00:00",
    "not_after": "2025-12-10T23:59:59",
    "serial_number": "0dea7458cb029724a7926e896fda5ed5",
    "result_count": 3
  },
  {
    "issuer_ca_id": 62123,
    "issuer_name": "C=US, O=DigiCert Inc, OU=www.digicert.com, CN=GeoTrust TLS RSA CA G1",
    "common_name": "uis.uat.usajobs.gov",
    "name_value": "login.uat.usajobs.gov\nlogin.usajobs.gov\nuis.uat.usajobs.gov\nusajobs.gov",
    "id": 17543021841,
    "entry_timestamp": "2025-04-01T00:07:12.961",
    "not_before": "2025-04-01T00:00:00",
    "not_after": "2026-04-01T23:59:59",
    "serial_number": "041e377c89fcf8ce4436c0a4f9399d72",
    "result_count": 5
  },
  {
    "issuer_ca_id": 62148,
    "issuer_name": "C=US, O=DigiCert Inc, OU=www.digicert.com, CN=GeoTrust RSA CA 2018",
    "common_name": "webadmin.uat.usajobs.gov",
    "name_value": "ac.drtest.usajobs.gov\nac.test.usajobs.gov\nac.uat.usajobs.gov\ndata.drtest.usajobs.gov\ndata.test.usajobs.gov\ndata.uat.usajobs.gov\ndrtest.usajobs.gov\nhelpdesk.drtest.usajobs.gov\nhelpdesk.uat.usajobs.gov\nhelp.drtest.usajobs.gov\nhelp.test.usajobs.gov\nhelp.uat.usajobs.gov\nlogin.drtest.usajobs.gov\nlogin.test.usajobs.gov\nmedia.drtest.usajobs.gov\nmedia.test.usajobs.gov\nmedia.uat.usajobs.gov\nopenopps.dev.usajobs.gov\nopenopps.test.usajobs.gov\nopenopps.uat.usajobs.gov\nresearch.test.usajobs.gov\nschemas.drtest.usajobs.gov\nschemas.test.usajobs.gov\nschemas.uat.usajobs.gov\ntest.usajobs.gov\nuat.usajobs.gov\nuis.test.usajobs.gov\nuis.uat.usajobs.gov\nwebadmin.drtest.usajobs.gov\nwebadmin.test.usajobs.gov\nwebadmin.uat.usajobs.gov\nwww.drtest.usajobs.gov\nwww.uat.usajobs.gov",
    "id": 16704299898,
    "entry_timestamp": "2025-02-13T00:17:04.491",
    "not_before": "2025-02-13T00:00:00",
    "not_after": "2026-02-13T23:59:59",
    "serial_number": "01d4f25ccc8e7b801377f0890033894b",
    "result_count": 34
  },
  {
    "issuer_ca_id": 185756,
    "issuer_name": "C=US, O=DigiCert Inc, CN=DigiCert TLS RSA SHA256 2020 CA1",
    "common_name": "*.uat.usajobs.gov",
    "name_value": "*.uat.usajobs.gov\nuat.usajobs.gov",
    "id": 15688732934,
    "entry_timestamp": "2024-12-10T00:16:03.924",
    "not_before": "2024-12-10T00:00:00",
    "not_after": "2025-12-10T23:59:59",
    "serial_number": "0dea7458cb029724a7926e896fda5ed5",
    "result_count": 3
  },
  {
    "issuer_ca_id": 185756,
    "issuer_name": "C=US, O=DigiCert Inc, CN=DigiCert TLS RSA SHA256 2020 CA1",
    "common_name": "*.uat.usajobs.gov",
    "name_value": "*.uat.usajobs.gov\nuat.usajobs.gov",
    "id": 15688711716,
    "entry_timestamp": "2024-12-10T00:13:37.995",
    "not_before": "2024-12-10T00:00:00",
    "not_after": "2025-12-10T23:59:59",
    "serial_number": "084adbb0db6ab4a0fa6f35e43bd9fb30",
    "result_count": 3
  },
  {
    "issuer_ca_id": 185756,
    "issuer_name": "C=US, O=DigiCert Inc, CN=DigiCert TLS RSA SHA256 2020 CA1",
    "common_name": "*.test.usajobs.gov",
    "name_value": "*.test.usajobs.gov\ntest.usajobs.gov",
    "id": 15658906936,
    "entry_timestamp": "2024-12-08T00:19:05.218",
    "not_before": "2024-12-08T00:00:00",
    "not_after": "2025-12-10T23:59:59",
    "serial_number": "05417a4f26254661e8268e3dbe125c56",
    "result_count": 3
  },
  {
    "issuer_ca_id": 185756,
    "issuer_name": "C=US, O=DigiCert Inc, CN=DigiCert TLS RSA SHA256 2020 CA1",
    "common_name": "*.test.usajobs.gov",
    "name_value": "*.test.usajobs.gov\ntest.usajobs.gov",
    "id": 15658812455,
    "entry_timestamp": "2024-12-08T00:10:14.736",
    "not_before": "2024-12-08T00:00:00",
    "not_after": "2025-12-10T23:59:59",
    "serial_number": "0fb3c345d38724ae3bb657898bfd95d9",
    "result_count": 3
  },
  {
    "issuer_ca_id": 185756,
    "issuer_name": "C=US, O=DigiCert Inc, CN=DigiCert TLS RSA SHA256 2020 CA1",
    "common_name": "*.usajobs.gov",
    "name_value": "*.usajobs.gov\nusajobs.gov",
    "id": 15215759106,
    "entry_timestamp": "2024-11-05T00:36:57.141",
    "not_before": "2024-11-05T00:00:00",
    "not_after": "2025-11-05T23:59:59",
    "serial_number": "0ffdb1dc64282610aa08b6a045fd6465",
    "result_count": 3
  }
]