[
  {
    "issuer_ca_id": 246719,
    "issuer_name": "C=US, O=Amazon, CN=Amazon RSA 2048 M01",
    "common_name": "ppms.gov",
    "name_value": "*.gsaauctions.gov\ngsaauctions.gov",
    "id": 25462125886,
    "entry_timestamp": "2026-04-10T01:57:25.15",
    "not_before": "2026-04-10T00:00:00",
    "not_after": "2026-10-24T23:59:59",
    "serial_number": "01baed2d8ac07c78550fe7f09d0b068d",
    "result_count": 2
  },
  {
    "issuer_ca_id": 295817,
    "issuer_name": "C=US, O=Let's Encrypt, CN=R13",
    "common_name": "staging.gsaauctions.gov",
    "name_value": "staging.gsaauctions.gov",
    "id": 24932770089,
    "entry_timestamp": "2026-03-12T01:46:27.021",
    "not_before": "2026-03-12T00:47:54",
    "not_after": "2026-06-10T00:47:53",
    "serial_number": "0632cc2ff1ec934a81e27c6dd7baaa53cb2c",
    "result_count": 2
  },
  {
    "issuer_ca_id": 295817,
    "issuer_name": "C=US, O=Let's Encrypt, CN=R13",
    "common_name": "staging.gsaauctions.gov",
    "name_value": "staging.gsaauctions.gov",
    "id": 24932751070,
    "entry_timestamp": "2026-03-12T01:46:25.285",
    "not_before": "2026-03-12T00:47:54",
    "not_after": "2026-06-10T00:47:53",
    "serial_number": "0632cc2ff1ec934a81e27c6dd7baaa53cb2c",
    "result_count": 2
  },
  {
    "issuer_ca_id": 247106,
    "issuer_name": "C=US, O=Amazon, CN=Amazon RSA 2048 M03",
    "common_name": "ppms.gov",
    "name_value": "*.gsaauctions.gov\ngsaauctions.gov",
    "id": 18319194097,
    "entry_timestamp": "2025-05-10T03:49:17.224",
    "not_before": "2025-05-10T00:00:00",
    "not_after": "2026-06-08T23:59:59",
    "serial_number": "0738b5587389b6dd93c0d383af1f1b7a",
    "result_count": 2
  },
  {
    "issuer_ca_id": 247106,
    "issuer_name": "C=US, O=Amazon, CN=Amazon RSA 2048 M03",
    "common_name": "ppms.gov",
    "name_value": "*.gsaauctions.gov\ngsaauctions.gov",
    "id": 18318347776,
    "entry_timestamp": "2025-05-10T02:41:24.785",
    "not_before": "2025-05-10T00:00:00",
    "not_after": "2026-06-08T23:59:59",
    "serial_number": "0738b5587389b6dd93c0d383af1f1b7a",
    "result_count": 2
  }
]