[
  {
    "issuer_ca_id": 204407,
    "issuer_name": "C=GB, O=Sectigo Limited, CN=Sectigo Public Server Authentication CA DV E36",
    "common_name": "usaspending.gov",
    "name_value": "*.usaspending.gov\nusaspending.gov",
    "id": 20106712034,
    "entry_timestamp": "2025-08-04T07:54:54.834",
    "not_before": "2025-08-04T00:00:00",
    "not_after": "2025-11-02T06:13:26",
    "serial_number": "00a8d030b035707fb57eb74cdc130a629e",
    "result_count": 3
  },
  {
    "issuer_ca_id": 204407,
    "issuer_name": "C=GB, O=Sectigo Limited, CN=Sectigo Public Server Authentication CA DV E36",
    "common_name": "usaspending.gov",
    "name_value": "*.usaspending.gov\nusaspending.gov",
    "id": 20106709747,
    "entry_timestamp": "2025-08-04T07:54:48.877",
    "not_before": "2025-08-04T00:00:00",
    "not_after": "2025-11-02T06:13:26",
    "serial_number": "00a8d030b035707fb57eb74cdc130a629e",
    "result_count": 3
  },
  {
    "issuer_ca_id": 204406,
    "issuer_name": "C=GB, O=Sectigo Limited, CN=Sectigo Public Server Authentication CA DV R36",
    "common_name": "usaspending.gov",
    "name_value": "*.usaspending.gov\nusaspending.gov",
    "id": 20105171823,
    "entry_timestamp": "2025-08-04T06:13:15.922",
    "not_before": "2025-08-04T00:00:00",
    "not_after": "2025-11-02T04:34:01",
    "serial_number": "19606b0591bfda3a66cbee210685e368",
    "result_count": 3
  },
  {
    "issuer_ca_id": 204406,
    "issuer_name": "C=GB, O=Sectigo Limited, CN=Sectigo Public Server Authentication CA DV R36",
    "common_name": "usaspending.gov",
    "name_value": "*.usaspending.gov\nusaspending.gov",
    "id": 20105171730,
    "entry_timestamp": "2025-08-04T06:13:14.426",
    "not_before": "2025-08-04T00:00:00",
    "not_after": "2025-11-02T04:34:01",
    "serial_number": "19606b0591bfda3a66cbee210685e368",
    "result_count": 3
  },
  {
    "issuer_ca_id": 286236,
    "issuer_name": "C=US, O=Google Trust Services, CN=WE1",
    "common_name": "usaspending.gov",
    "name_value": "*.usaspending.gov\nusaspending.gov",
    "id": 19668787264,
    "entry_timestamp": "2025-07-15T00:20:16.678",
    "not_before": "2025-07-14T23:20:16",
    "not_after": "2025-10-13T00:19:52",
    "serial_number": "605c50d0f43983150dbe7498ea68d8d6",
    "result_count": 3
  },
  {
    "issuer_ca_id": 286242,
    "issuer_name": "C=US, O=Google Trust Services, CN=WR1",
    "common_name": "usaspending.gov",
    "name_value": "*.usaspending.gov\nusaspending.gov",
    "id": 19668777642,
    "entry_timestamp": "2025-07-15T00:19:46.382",
    "not_before": "2025-07-14T23:19:45",
    "not_after": "2025-10-13T00:18:14",
    "serial_number": "00d73dbcd43deb1c58112349abf0ad8ed7",
    "result_count": 3
  },
  {
    "issuer_ca_id": 204407,
    "issuer_name": "C=GB, O=Sectigo Limited, CN=Sectigo Public Server Authentication CA DV E36",
    "common_name": "usaspending.gov",
    "name_value": "*.usaspending.gov\nusaspending.gov",
    "id": 18965999428,
    "entry_timestamp": "2025-06-11T23:05:35.435",
    "not_before": "2025-06-11T00:00:00",
    "not_after": "2025-09-06T04:22:19",
    "serial_number": "00a134938973da4d767c58448c5fbd70ad",
    "result_count": 3
  },
  {
    "issuer_ca_id": 204407,
    "issuer_name": "C=GB, O=Sectigo Limited, CN=Sectigo Public Server Authentication CA DV E36",
    "common_name": "usaspending.gov",
    "name_value": "*.usaspending.gov\nusaspending.gov",
    "id": 18965999953,
    "entry_timestamp": "2025-06-11T23:05:34.795",
    "not_before": "2025-06-11T00:00:00",
    "not_after": "2025-09-06T04:22:19",
    "serial_number": "00a134938973da4d767c58448c5fbd70ad",
    "result_count": 3
  },
  {
    "issuer_ca_id": 204406,
    "issuer_name": "C=GB, O=Sectigo Limited, CN=Sectigo Public Server Authentication CA DV R36",
    "common_name": "usaspending.gov",
    "name_value": "*.usaspending.gov\nusaspending.gov",
    "id": 18884249933,
    "entry_timestamp": "2025-06-08T04:22:07.032",
    "not_before": "2025-06-08T00:00:00",
    "not_after": "2025-09-04T03:10:09",
    "serial_number": "00eb084623f0b24ae2d45d616b6a01a4f5",
    "result_count": 3
  },
  {
    "issuer_ca_id": 204406,
    "issuer_name": "C=GB, O=Sectigo Limited, CN=Sectigo Public Server Authentication CA DV R36",
    "common_name": "usaspending.gov",
    "name_value": "*.usaspending.gov\nusaspending.gov",
    "id": 18884249571,
    "entry_timestamp": "2025-06-08T04:22:05.897",
    "not_before": "2025-06-08T00:00:00",
    "not_after": "2025-09-04T03:10:09",
    "serial_number": "00eb084623f0b24ae2d45d616b6a01a4f5",
    "result_count": 3
  },
  {
    "issuer_ca_id": 105493,
    "issuer_name": "C=GB, ST=Greater Manchester, L=Salford, O=Sectigo Limited, CN=Sectigo RSA Domain Validation Secure Server CA",
    "common_name": null,
    "name_value": "usaspending.gov",
    "id": 18674406003,
    "entry_timestamp": "2025-05-28T14:15:18.128",
    "not_before": "2025-05-28T00:00:00",
    "not_after": "2026-05-28T23:59:59",
    "serial_number": "7d99ae25bc621eebf2292a6bca9f3ea9",
    "result_count": 1
  },
  {
    "issuer_ca_id": 105493,
    "issuer_name": "C=GB, ST=Greater Manchester, L=Salford, O=Sectigo Limited, CN=Sectigo RSA Domain Validation Secure Server CA",
    "common_name": null,
    "name_value": "usaspending.gov",
    "id": 18674405654,
    "entry_timestamp": "2025-05-28T14:15:17.054",
    "not_before": "2025-05-28T00:00:00",
    "not_after": "2026-05-28T23:59:59",
    "serial_number": "7d99ae25bc621eebf2292a6bca9f3ea9",
    "result_count": 1
  },
  {
    "issuer_ca_id": 365075,
    "issuer_name": "C=US, O=SSL Corporation, CN=Entrust OV TLS Issuing RSA CA 1",
    "common_name": "prod-databricks.usaspending.gov",
    "name_value": "prod-databricks.usaspending.gov",
    "id": 18580443431,
    "entry_timestamp": "2025-05-23T16:33:36.127",
    "not_before": "2025-05-23T16:23:34",
    "not_after": "2026-06-23T04:00:00",
    "serial_number": "0b70688ec8c777209c197bfe9bc55223",
    "result_count": 2
  },
  {
    "issuer_ca_id": 365075,
    "issuer_name": "C=US, O=SSL Corporation, CN=Entrust OV TLS Issuing RSA CA 1",
    "common_name": "staging-databricks.usaspending.gov",
    "name_value": "staging-databricks.usaspending.gov",
    "id": 18580443509,
    "entry_timestamp": "2025-05-23T16:33:36.056",
    "not_before": "2025-05-23T16:23:34",
    "not_after": "2026-06-23T04:00:00",
    "serial_number": "48b84d076963402a73f94f7bf74731c7",
    "result_count": 2
  },
  {
    "issuer_ca_id": 286236,
    "issuer_name": "C=US, O=Google Trust Services, CN=WE1",
    "common_name": "usaspending.gov",
    "name_value": "*.usaspending.gov\nusaspending.gov",
    "id": 18450294803,
    "entry_timestamp": "2025-05-16T23:46:21.573",
    "not_before": "2025-05-16T22:46:21",
    "not_after": "2025-08-14T23:46:13",
    "serial_number": "0080de2283da6dde480e1a53d4eff20c01",
    "result_count": 3
  },
  {
    "issuer_ca_id": 286242,
    "issuer_name": "C=US, O=Google Trust Services, CN=WR1",
    "common_name": "usaspending.gov",
    "name_value": "*.usaspending.gov\nusaspending.gov",
    "id": 18450306630,
    "entry_timestamp": "2025-05-16T23:46:08.042",
    "not_before": "2025-05-16T22:46:07",
    "not_after": "2025-08-14T23:44:29",
    "serial_number": "56643794b321da1213572f6a726167c6",
    "result_count": 3
  },
  {
    "issuer_ca_id": 365075,
    "issuer_name": "C=US, O=SSL Corporation, CN=Entrust OV TLS Issuing RSA CA 1",
    "common_name": "qat-databricks.usaspending.gov",
    "name_value": "qat-databricks.usaspending.gov",
    "id": 16958325438,
    "entry_timestamp": "2025-03-07T16:58:25.91",
    "not_before": "2025-03-07T16:48:24",
    "not_after": "2026-04-04T15:28:29",
    "serial_number": "15302c744f011260aa3bfd17aca7838b",
    "result_count": 2
  },
  {
    "issuer_ca_id": 1586,
    "issuer_name": "C=US, O=\"Entrust, Inc.\", OU=See www.entrust.net/legal-terms, OU=\"(c) 2012 Entrust, Inc. - for authorized use only\", CN=Entrust Certification Authority - L1K",
    "common_name": "treasury.gov",
    "name_value": "usaspending.gov",
    "id": 15061723424,
    "entry_timestamp": "2024-10-24T03:23:52.974",
    "not_before": "2024-10-04T10:11:50",
    "not_after": "2025-11-03T10:11:49",
    "serial_number": "6d25c4c3a1049ca4d9fc5d62dc456d0a",
    "result_count": 1
  },
  {
    "issuer_ca_id": 1586,
    "issuer_name": "C=US, O=\"Entrust, Inc.\", OU=See www.entrust.net/legal-terms, OU=\"(c) 2012 Entrust, Inc. - for authorized use only\", CN=Entrust Certification Authority - L1K",
    "common_name": "treasury.gov",
    "name_value": "usaspending.gov",
    "id": 14794287112,
    "entry_timestamp": "2024-10-04T10:11:50.928",
    "not_before": "2024-10-04T10:11:50",
    "not_after": "2025-11-03T10:11:49",
    "serial_number": "6d25c4c3a1049ca4d9fc5d62dc456d0a",
    "result_count": 1
  },
  {
    "issuer_ca_id": 1586,
    "issuer_name": "C=US, O=\"Entrust, Inc.\", OU=See www.entrust.net/legal-terms, OU=\"(c) 2012 Entrust, Inc. - for authorized use only\", CN=Entrust Certification Authority - L1K",
    "common_name": "usaspending.gov",
    "name_value": "*.usaspending.gov\nusaspending.gov",
    "id": 14586619657,
    "entry_timestamp": "2024-09-17T18:01:31.65",
    "not_before": "2024-09-17T18:01:31",
    "not_after": "2025-10-17T18:01:30",
    "serial_number": "58991cab07d338e1a2d8c3f7fc6ed511",
    "result_count": 3
  }
]